flake8_vedro/__init__.py
flake8_vedro/config.py
flake8_vedro/defaults.py
flake8_vedro/plugins.py
flake8_vedro/abstract_checkers/__init__.py
flake8_vedro/abstract_checkers/context_checker.py
flake8_vedro/abstract_checkers/scenario_checker.py
flake8_vedro/abstract_checkers/scenario_helper.py
flake8_vedro/abstract_checkers/step_checker.py
flake8_vedro/errors/__init__.py
flake8_vedro/errors/errors.py
flake8_vedro/helpers/__init__.py
flake8_vedro/helpers/imported_from_dir_methods.py
flake8_vedro/helpers/scope_variables.py
flake8_vedro/helpers/unwrap_name.py
flake8_vedro/types/__init__.py
flake8_vedro/types/types.py
flake8_vedro/visitors/__init__.py
flake8_vedro/visitors/_visitor_with_filename.py
flake8_vedro/visitors/context_visitor.py
flake8_vedro/visitors/scenario_visitor.py
flake8_vedro/visitors/context_checkers/__init__.py
flake8_vedro/visitors/context_checkers/assert_checker.py
flake8_vedro/visitors/scenario_checkers/__init__.py
flake8_vedro/visitors/scenario_checkers/decorator_checker.py
flake8_vedro/visitors/scenario_checkers/location_checker.py
flake8_vedro/visitors/scenario_checkers/parametrization_call_checker.py
flake8_vedro/visitors/scenario_checkers/parametrization_limit_checker.py
flake8_vedro/visitors/scenario_checkers/parametrization_subject_checker.py
flake8_vedro/visitors/scenario_checkers/parent_checker.py
flake8_vedro/visitors/scenario_checkers/subject_checker.py
flake8_vedro/visitors/steps_checkers/__init__.py
flake8_vedro/visitors/steps_checkers/assert_checker.py
flake8_vedro/visitors/steps_checkers/interfaces_checker.py
flake8_vedro/visitors/steps_checkers/name_checker.py
flake8_vedro/visitors/steps_checkers/no_assert_checker.py
flake8_vedro/visitors/steps_checkers/order_checker.py
flake8_vedro/visitors/steps_checkers/scope_partial_redefinition_checker.py
flake8_vedro/visitors/steps_checkers/scope_redefinition_checker.py
flake8_vedro/visitors/steps_checkers/then_checker.py
flake8_vedro/visitors/steps_checkers/unused_scope_checker.py
flake8_vedro-1.1.1.dist-info/licenses/LICENSE
flake8_vedro-1.1.1.dist-info/METADATA
flake8_vedro-1.1.1.dist-info/WHEEL
flake8_vedro-1.1.1.dist-info/entry_points.txt
flake8_vedro-1.1.1.dist-info/top_level.txt
flake8_vedro-1.1.1.dist-info/RECORD
