Metadata-Version: 2.4
Name: flake8-vedro
Version: 1.1.1
Summary: flake8 based linter for vedro framework
Home-page: https://github.com/mytestopia/flake8-vedro
Author: Anna
Author-email: testopia13@gmail.com
License: Apache-2.0
Classifier: License :: OSI Approved :: Apache Software License
Classifier: Programming Language :: Python :: 3.10
Classifier: Programming Language :: Python :: 3.11
Requires-Python: >=3.10
License-File: LICENSE
Requires-Dist: flake8<7.0,>=6.0
Requires-Dist: flake8-plugin-utils<2.0,>=1.3.2
Dynamic: author
Dynamic: author-email
Dynamic: classifier
Dynamic: description
Dynamic: description-content-type
Dynamic: home-page
Dynamic: license
Dynamic: license-file
Dynamic: requires-dist
Dynamic: requires-python
Dynamic: summary
